pypkgsroyce/__init__.py
pypkgsroyce/pypkgsroyce.py
pypkgsroyce-0.1.0.dist-info/LICENSE
pypkgsroyce-0.1.0.dist-info/WHEEL
pypkgsroyce-0.1.0.dist-info/METADATA
pypkgsroyce-0.1.0.dist-info/RECORD
